{"type": "FeatureCollection", "features": [{"type": "Feature", "geometry": {"type": "Point", "coordinates": [38.494828, 59.236593]}, "properties": {"name": "Шекснинская ГЭС", "address": "пос. Шексна, р. Шексна"}}]}